>>>General Information<<<
Minor version:      	0
Major version:      	46
Constant pool count:	46
Access flags:       	0x21
This class:         	CP INFO #9 < Hello >
Super class:        	CP INFO #10 < java/lang/Object >
Interfaces count:   	0
Fields count:       	2
Methods count:      	6
Attributes count:   	1


>>>Constant Pool<<<
[1]CONSTANT_Methodref_info:
	Class name:          	CP INFO #10 < java/lang/Object >
	Name and type:       	CP INFO #30 < <init>()V >
[2]CONSTANT_Fieldref_info:
	Class name:          	CP INFO #9 < Hello >
	Name and type:       	CP INFO #31 < teste_intI >
[3]CONSTANT_Double_info:
	High bytes:          	0x40026666
	Low bytes:           	0x66666666
	Double:              	2.300000
[4](large numeric continued)
[5]CONSTANT_Fieldref_info:
	Class name:          	CP INFO #9 < Hello >
	Name and type:       	CP INFO #32 < teste_doubleD >
[6]CONSTANT_Fieldref_info:
	Class name:          	CP INFO #33 < java/lang/System >
	Name and type:       	CP INFO #34 < outLjava/io/PrintStream; >
[7]CONSTANT_String_info:
	String:              	CP INFO #35 < Hello! >
[8]CONSTANT_Methodref_info:
	Class name:          	CP INFO #36 < java/io/PrintStream >
	Name and type:       	CP INFO #37 < println(Ljava/lang/String;)V >
[9]CONSTANT_Class_info:
	Class name:          	CP INFO #38 < Hello >
[10]CONSTANT_Class_info:
	Class name:          	CP INFO #39 < java/lang/Object >
[11]CONSTANT_Utf8_info:
	Length of byte array:	9
	Length of string:    	9
	String:              	teste_int
[12]CONSTANT_Utf8_info:
	Length of byte array:	1
	Length of string:    	1
	String:              	I
[13]CONSTANT_Utf8_info:
	Length of byte array:	12
	Length of string:    	12
	String:              	teste_double
[14]CONSTANT_Utf8_info:
	Length of byte array:	1
	Length of string:    	1
	String:              	D
[15]CONSTANT_Utf8_info:
	Length of byte array:	6
	Length of string:    	6
	String:              	<init>
[16]CONSTANT_Utf8_info:
	Length of byte array:	3
	Length of string:    	3
	String:              	()V
[17]CONSTANT_Utf8_info:
	Length of byte array:	4
	Length of string:    	4
	String:              	Code
[18]CONSTANT_Utf8_info:
	Length of byte array:	15
	Length of string:    	15
	String:              	LineNumberTable
[19]CONSTANT_Utf8_info:
	Length of byte array:	7
	Length of string:    	7
	String:              	get_int
[20]CONSTANT_Utf8_info:
	Length of byte array:	3
	Length of string:    	3
	String:              	()I
[21]CONSTANT_Utf8_info:
	Length of byte array:	10
	Length of string:    	10
	String:              	get_double
[22]CONSTANT_Utf8_info:
	Length of byte array:	3
	Length of string:    	3
	String:              	()D
[23]CONSTANT_Utf8_info:
	Length of byte array:	7
	Length of string:    	7
	String:              	set_int
[24]CONSTANT_Utf8_info:
	Length of byte array:	4
	Length of string:    	4
	String:              	(I)V
[25]CONSTANT_Utf8_info:
	Length of byte array:	10
	Length of string:    	10
	String:              	set_double
[26]CONSTANT_Utf8_info:
	Length of byte array:	4
	Length of string:    	4
	String:              	(D)V
[27]CONSTANT_Utf8_info:
	Length of byte array:	5
	Length of string:    	5
	String:              	hello
[28]CONSTANT_Utf8_info:
	Length of byte array:	10
	Length of string:    	10
	String:              	SourceFile
[29]CONSTANT_Utf8_info:
	Length of byte array:	10
	Length of string:    	10
	String:              	Hello.java
[30]CONSTANT_NameAndType_info:
	Name:                	CP INFO #15 < <init> >
	Descriptor:          	CP INFO #16 < ()V >
[31]CONSTANT_NameAndType_info:
	Name:                	CP INFO #11 < teste_int >
	Descriptor:          	CP INFO #12 < I >
[32]CONSTANT_NameAndType_info:
	Name:                	CP INFO #13 < teste_double >
	Descriptor:          	CP INFO #14 < D >
[33]CONSTANT_Class_info:
	Class name:          	CP INFO #40 < java/lang/System >
[34]CONSTANT_NameAndType_info:
	Name:                	CP INFO #41 < out >
	Descriptor:          	CP INFO #42 < Ljava/io/PrintStream; >
[35]CONSTANT_Utf8_info:
	Length of byte array:	6
	Length of string:    	6
	String:              	Hello!
[36]CONSTANT_Class_info:
	Class name:          	CP INFO #43 < java/io/PrintStream >
[37]CONSTANT_NameAndType_info:
	Name:                	CP INFO #44 < println >
	Descriptor:          	CP INFO #45 < (Ljava/lang/String;)V >
[38]CONSTANT_Utf8_info:
	Length of byte array:	5
	Length of string:    	5
	String:              	Hello
[39]CONSTANT_Utf8_info:
	Length of byte array:	16
	Length of string:    	16
	String:              	java/lang/Object
[40]CONSTANT_Utf8_info:
	Length of byte array:	16
	Length of string:    	16
	String:              	java/lang/System
[41]CONSTANT_Utf8_info:
	Length of byte array:	3
	Length of string:    	3
	String:              	out
[42]CONSTANT_Utf8_info:
	Length of byte array:	21
	Length of string:    	21
	String:              	Ljava/io/PrintStream;
[43]CONSTANT_Utf8_info:
	Length of byte array:	19
	Length of string:    	19
	String:              	java/io/PrintStream
[44]CONSTANT_Utf8_info:
	Length of byte array:	7
	Length of string:    	7
	String:              	println
[45]CONSTANT_Utf8_info:
	Length of byte array:	21
	Length of string:    	21
	String:              	(Ljava/lang/String;)V

>>>Fields<<<
[0]teste_int
	Access Flags:    	2
	Name Index:      	CP INFO #11 teste_int
	Descriptor Index:	CP INFO #12 I
	Attributes Count:	0
[1]teste_double
	Access Flags:    	2
	Name Index:      	CP INFO #13 teste_double
	Descriptor Index:	CP INFO #14 D
	Attributes Count:	0

>>>Methods<<<

Methods Count: 	6
[0]<init>
	Access Flags:    	1
	Name Index:      	CP INFO #15 < <init> >
	Descriptor Index:	CP INFO #16 < ()V >
	Attributes Count:	1
	[0]Code
		Name Index:      	CP INFO #17 < Code >
		Attribute Lenght:	53
		Max Stack:          	3
		Max Locals:         	1
		Code Length:        	17
		Code:	 
					0: aload_0	
					1: invokespecial	0	1	
					4: aload_0	
					5: iconst_3	
					6: putfield	0	2	
					9: aload_0	
					10: ldc2_w	0	3	
					13: putfield	0	5	
					16: return	

		Exception Table Length: 	0
		Code Attributes Count:	1
		[0]LineNumberTable
		Name Index:      	CP INFO #18 < LineNumberTable >
		Attribute Lenght:	18
		Number of Lines:	4
		Line Number: 	5
		Start PC:    	0
		Line Number: 	2
		Start PC:    	4
		Line Number: 	3
		Start PC:    	9
		Line Number: 	7
		Start PC:    	16
[1]get_int
	Access Flags:    	1
	Name Index:      	CP INFO #19 < get_int >
	Descriptor Index:	CP INFO #20 < ()I >
	Attributes Count:	1
	[0]Code
		Name Index:      	CP INFO #17 < Code >
		Attribute Lenght:	29
		Max Stack:          	1
		Max Locals:         	1
		Code Length:        	5
		Code:	 
					0: aload_0	
					1: getfield	0	2	
					4: ireturn	

		Exception Table Length: 	0
		Code Attributes Count:	1
		[0]LineNumberTable
		Name Index:      	CP INFO #18 < LineNumberTable >
		Attribute Lenght:	6
		Number of Lines:	1
		Line Number: 	10
		Start PC:    	0
[2]get_double
	Access Flags:    	1
	Name Index:      	CP INFO #21 < get_double >
	Descriptor Index:	CP INFO #22 < ()D >
	Attributes Count:	1
	[0]Code
		Name Index:      	CP INFO #17 < Code >
		Attribute Lenght:	29
		Max Stack:          	2
		Max Locals:         	1
		Code Length:        	5
		Code:	 
					0: aload_0	
					1: getfield	0	5	
					4: dreturn	

		Exception Table Length: 	0
		Code Attributes Count:	1
		[0]LineNumberTable
		Name Index:      	CP INFO #18 < LineNumberTable >
		Attribute Lenght:	6
		Number of Lines:	1
		Line Number: 	14
		Start PC:    	0
[3]set_int
	Access Flags:    	1
	Name Index:      	CP INFO #23 < set_int >
	Descriptor Index:	CP INFO #24 < (I)V >
	Attributes Count:	1
	[0]Code
		Name Index:      	CP INFO #17 < Code >
		Attribute Lenght:	34
		Max Stack:          	2
		Max Locals:         	2
		Code Length:        	6
		Code:	 
					0: aload_0	
					1: iload_1	
					2: putfield	0	2	
					5: return	

		Exception Table Length: 	0
		Code Attributes Count:	1
		[0]LineNumberTable
		Name Index:      	CP INFO #18 < LineNumberTable >
		Attribute Lenght:	10
		Number of Lines:	2
		Line Number: 	18
		Start PC:    	0
		Line Number: 	19
		Start PC:    	5
[4]set_double
	Access Flags:    	1
	Name Index:      	CP INFO #25 < set_double >
	Descriptor Index:	CP INFO #26 < (D)V >
	Attributes Count:	1
	[0]Code
		Name Index:      	CP INFO #17 < Code >
		Attribute Lenght:	34
		Max Stack:          	3
		Max Locals:         	3
		Code Length:        	6
		Code:	 
					0: aload_0	
					1: dload_1	
					2: putfield	0	5	
					5: return	

		Exception Table Length: 	0
		Code Attributes Count:	1
		[0]LineNumberTable
		Name Index:      	CP INFO #18 < LineNumberTable >
		Attribute Lenght:	10
		Number of Lines:	2
		Line Number: 	22
		Start PC:    	0
		Line Number: 	23
		Start PC:    	5
[5]hello
	Access Flags:    	1
	Name Index:      	CP INFO #27 < hello >
	Descriptor Index:	CP INFO #16 < ()V >
	Attributes Count:	1
	[0]Code
		Name Index:      	CP INFO #17 < Code >
		Attribute Lenght:	37
		Max Stack:          	2
		Max Locals:         	1
		Code Length:        	9
		Code:	 
					0: getstatic	0	6	
					3: ldc	7	
					5: invokevirtual	0	8	
					8: return	

		Exception Table Length: 	0
		Code Attributes Count:	1
		[0]LineNumberTable
		Name Index:      	CP INFO #18 < LineNumberTable >
		Attribute Lenght:	10
		Number of Lines:	2
		Line Number: 	26
		Start PC:    	0
		Line Number: 	27
		Start PC:    	8

>>>Attributes<<<

Attributes Count: 	1
	[0]SourceFile
		Name Index:      	CP INFO #28 < SourceFile >
		Attribute Lenght:	2
		Source File Index: 	CP INFO #29 < Hello.java >
